lyra/__init__.py
lyra/analyser.py
lyra/async_client.py
lyra/base_client.py
lyra/cli.py
lyra/constants.py
lyra/enums.py
lyra/http_client.py
lyra/lyra.py
lyra/utils.py
lyra/ws_client.py
lyra_v2_client-0.2.11.dist-info/METADATA
lyra_v2_client-0.2.11.dist-info/WHEEL
lyra_v2_client-0.2.11.dist-info/entry_points.txt
lyra_v2_client-0.2.11.dist-info/RECORD
