Metadata-Version: 2.1
Name: lyra-v2-client
Version: 0.2.11
Summary: 
Author: 8baller
Author-email: 8ball030@gmail.com
Requires-Python: >=3.8.1,<3.12
Classifier: Programming Language :: Python :: 3
Classifier: Programming Language :: Python :: 3.9
Classifier: Programming Language :: Python :: 3.10
Classifier: Programming Language :: Python :: 3.11
Requires-Dist: pandas (>=1,<=3)
Requires-Dist: python-dotenv (>=0.14.0,<0.18.0)
Requires-Dist: requests (>=2,<3)
Requires-Dist: rich-click (>=1.7.1,<2.0.0)
Requires-Dist: setuptools (>=68.2.2,<70)
Requires-Dist: web3 (>=6,<7)
Requires-Dist: websocket-client (>=0.32.0,<1)
